snapinfo/__init__.py
snapinfo/info.py
snapinfo-0.0.1.dist-info/LICENSE
snapinfo-0.0.1.dist-info/METADATA
snapinfo-0.0.1.dist-info/WHEEL
snapinfo-0.0.1.dist-info/top_level.txt
snapinfo-0.0.1.dist-info/RECORD
